{
  "project_info": {
    "project_number": "49320958191",
    "firebase_url": "https://entranceiq-bde28.firebaseio.com",
    "project_id": "entranceiq-bde28",
    "storage_bucket": "entranceiq-bde28.appspot.com"
  },
  "client": [
    {
      "client_info": {
        "mobilesdk_app_id": "1:49320958191:android:5f9e5867d3aeaa89",
        "android_client_info": {
          "package_name": "com.entranceiq.testseries"
        }
      },
      "oauth_client": [
        {
          "client_id": "49320958191-0mnt1mi81f8ifemtef4ffrj3mrj45tbc.apps.googleusercontent.com",
          "client_type": 1,
          "android_info": {
            "package_name": "com.entranceiq.testseries",
            "certificate_hash": "c53ddd6f9c8bf151f77333cb7ae1b4111e6add49"
          }
        },
        {
          "client_id": "49320958191-vsvdcvo5sd3ss92i7mhpq375f4halb03.apps.googleusercontent.com",
          "client_type": 3
        }
      ],
      "api_key": [
        {
          "current_key": "AIzaSyCeVUgqZqwTUK25ZRTOG1Osu8gxTUDyYc8"
        }
      ],
      "services": {
        "analytics_service": {
          "status": 1
        },
        "appinvite_service": {
          "status": 2,
          "other_platform_oauth_client": [
            {
              "client_id": "49320958191-vsvdcvo5sd3ss92i7mhpq375f4halb03.apps.googleusercontent.com",
              "client_type": 3
            }
          ]
        },
        "ads_service": {
          "status": 2
        }
      }
    }
  ],
  "configuration_version": "1"
}